[
  {
    "Sex": "FEMALE",
    "Reporting Type": "G",
    "series": "SI_COV_MATNL",
    "goal": "1",
    "target": "1.3",
    "indicator": "1.3.1",
    "seriesDescription": "[ILO] Proportion of mothers with newborns receiving maternity cash benefit (%)",
    "values": [
      {
        "year": 2020.0,
        "value": 14.0
      }
    ],
    "targets": {
      "targetValue": 80,
      "type": "max"
    }
  },
  {
    "Sex": "FEMALE",
    "Reporting Type": "G",
    "series": "SI_COV_CHLD",
    "goal": "1",
    "target": "1.3",
    "indicator": "1.3.1",
    "seriesDescription": "[ILO] Proportion of children/households receiving child/family cash benefit, by sex (%)",
    "values": [
      {
        "year": 2020.0,
        "value": 16.6
      }
    ],
    "targets": {
      "targetValue": 80,
      "type": "max"
    }
  },
  {
    "Sex": "MALE",
    "Reporting Type": "G",
    "series": "SI_COV_CHLD",
    "goal": "1",
    "target": "1.3",
    "indicator": "1.3.1",
    "seriesDescription": "[ILO] Proportion of children/households receiving child/family cash benefit, by sex (%)",
    "values": [
      {
        "year": 2020.0,
        "value": 16.3
      }
    ],
    "targets": {
      "targetValue": 80,
      "type": "max"
    }
  },
  {
    "Sex": "BOTHSEX",
    "Reporting Type": "G",
    "series": "SI_COV_CHLD",
    "goal": "1",
    "target": "1.3",
    "indicator": "1.3.1",
    "seriesDescription": "[ILO] Proportion of children/households receiving child/family cash benefit, by sex (%)",
    "values": [
      {
        "year": 2020.0,
        "value": 16.4
      }
    ],
    "targets": {
      "targetValue": 80,
      "type": "max"
    }
  },
  {
    "Sex": "BOTHSEX",
    "Reporting Type": "G",
    "series": "SI_COV_UEMP",
    "goal": "1",
    "target": "1.3",
    "indicator": "1.3.1",
    "seriesDescription": "[ILO] Proportion of unemployed persons receiving unemployment cash benefit, by sex (%)",
    "values": [
      {
        "year": 2005.0,
        "value": 32.5
      },
      {
        "year": 2007.0,
        "value": 16.4
      },
      {
        "year": 2009.0,
        "value": 32.7
      },
      {
        "year": 2010.0,
        "value": 14.6
      },
      {
        "year": 2011.0,
        "value": 13.0
      },
      {
        "year": 2020.0,
        "value": 11.1
      }
    ],
    "targets": {
      "targetValue": 80,
      "type": "max"
    }
  },
  {
    "Sex": "FEMALE",
    "Reporting Type": "G",
    "series": "SI_COV_UEMP",
    "goal": "1",
    "target": "1.3",
    "indicator": "1.3.1",
    "seriesDescription": "[ILO] Proportion of unemployed persons receiving unemployment cash benefit, by sex (%)",
    "values": [
      {
        "year": 2020.0,
        "value": 15.3
      }
    ],
    "targets": {
      "targetValue": 80,
      "type": "max"
    }
  },
  {
    "Sex": "MALE",
    "Reporting Type": "G",
    "series": "SI_COV_UEMP",
    "goal": "1",
    "target": "1.3",
    "indicator": "1.3.1",
    "seriesDescription": "[ILO] Proportion of unemployed persons receiving unemployment cash benefit, by sex (%)",
    "values": [
      {
        "year": 2020.0,
        "value": 8.1
      }
    ],
    "targets": {
      "targetValue": 80,
      "type": "max"
    }
  },
  {
    "Sex": "BOTHSEX",
    "Reporting Type": "G",
    "series": "SI_COV_VULN",
    "goal": "1",
    "target": "1.3",
    "indicator": "1.3.1",
    "seriesDescription": "[ILO] Proportion of vulnerable population receiving social assistance cash benefit, by sex (%)",
    "values": [
      {
        "year": 2020.0,
        "value": 19.9
      }
    ],
    "targets": {
      "targetValue": 80,
      "type": "max"
    }
  },
  {
    "Sex": "BOTHSEX",
    "Reporting Type": "G",
    "series": "SI_COV_BENFTS",
    "goal": "1",
    "target": "1.3",
    "indicator": "1.3.1",
    "seriesDescription": "[ILO] Proportion of population covered by at least one social protection benefit, by sex (%)",
    "values": [
      {
        "year": 2020.0,
        "value": 76.7
      }
    ],
    "targets": {
      "targetValue": 80,
      "type": "max"
    }
  },
  {
    "Sex": "MALE",
    "Reporting Type": "G",
    "series": "SI_COV_BENFTS",
    "goal": "1",
    "target": "1.3",
    "indicator": "1.3.1",
    "seriesDescription": "[ILO] Proportion of population covered by at least one social protection benefit, by sex (%)",
    "values": [
      {
        "year": 2020.0,
        "value": 76.0
      }
    ],
    "targets": {
      "targetValue": 80,
      "type": "max"
    }
  },
  {
    "Sex": "FEMALE",
    "Reporting Type": "G",
    "series": "SI_COV_BENFTS",
    "goal": "1",
    "target": "1.3",
    "indicator": "1.3.1",
    "seriesDescription": "[ILO] Proportion of population covered by at least one social protection benefit, by sex (%)",
    "values": [
      {
        "year": 2020.0,
        "value": 77.1
      }
    ],
    "targets": {
      "targetValue": 80,
      "type": "max"
    }
  },
  {
    "Sex": "BOTHSEX",
    "Reporting Type": "G",
    "series": "SI_COV_PENSN",
    "goal": "1",
    "target": "1.3",
    "indicator": "1.3.1",
    "seriesDescription": "[ILO] Proportion of population above statutory pensionable age receiving a pension, by sex (%)",
    "values": [
      {
        "year": 2020.0,
        "value": 87.6
      }
    ],
    "targets": {
      "targetValue": 80,
      "type": "max"
    }
  },
  {
    "Sex": "MALE",
    "Reporting Type": "G",
    "series": "SI_COV_PENSN",
    "goal": "1",
    "target": "1.3",
    "indicator": "1.3.1",
    "seriesDescription": "[ILO] Proportion of population above statutory pensionable age receiving a pension, by sex (%)",
    "values": [
      {
        "year": 2020.0,
        "value": 84.2
      }
    ],
    "targets": {
      "targetValue": 80,
      "type": "max"
    }
  },
  {
    "Sex": "FEMALE",
    "Reporting Type": "G",
    "series": "SI_COV_PENSN",
    "goal": "1",
    "target": "1.3",
    "indicator": "1.3.1",
    "seriesDescription": "[ILO] Proportion of population above statutory pensionable age receiving a pension, by sex (%)",
    "values": [
      {
        "year": 2020.0,
        "value": 89.8
      }
    ],
    "targets": {
      "targetValue": 80,
      "type": "max"
    }
  },
  {
    "Name of international institution": "ADB",
    "Reporting Type": "G",
    "series": "SG_INT_MBRDEV",
    "goal": "10",
    "target": "10.6",
    "indicator": "10.6.1",
    "seriesDescription": "Proportion of members of developing countries in international organizations, by organization (%)",
    "values": [
      {
        "year": 2000.0,
        "value": 1.6949
      },
      {
        "year": 2005.0,
        "value": 1.5625
      },
      {
        "year": 2010.0,
        "value": 1.4925
      },
      {
        "year": 2015.0,
        "value": 1.4925
      },
      {
        "year": 2016.0,
        "value": 1.4925
      },
      {
        "year": 2017.0,
        "value": 1.4925
      },
      {
        "year": 2018.0,
        "value": 1.4925
      },
      {
        "year": 2019.0,
        "value": 1.47059
      },
      {
        "year": 2020.0,
        "value": 1.47058823529412
      },
      {
        "year": 2000.0,
        "value": 1.6949
      },
      {
        "year": 2005.0,
        "value": 1.5625
      },
      {
        "year": 2010.0,
        "value": 1.4925
      },
      {
        "year": 2015.0,
        "value": 1.4925
      },
      {
        "year": 2016.0,
        "value": 1.4925
      },
      {
        "year": 2017.0,
        "value": 1.4925
      },
      {
        "year": 2018.0,
        "value": 1.4925
      },
      {
        "year": 2019.0,
        "value": 1.47059
      },
      {
        "year": 2020.0,
        "value": 1.47058823529412
      }
    ],
    "targets": null
  },
  {
    "Name of international institution": "ADB",
    "Reporting Type": "G",
    "series": "SG_INT_MBRDEV",
    "goal": "16",
    "target": "16.8",
    "indicator": "16.8.1",
    "seriesDescription": "Proportion of members of developing countries in international organizations, by organization (%)",
    "values": [
      {
        "year": 2000.0,
        "value": 1.6949
      },
      {
        "year": 2005.0,
        "value": 1.5625
      },
      {
        "year": 2010.0,
        "value": 1.4925
      },
      {
        "year": 2015.0,
        "value": 1.4925
      },
      {
        "year": 2016.0,
        "value": 1.4925
      },
      {
        "year": 2017.0,
        "value": 1.4925
      },
      {
        "year": 2018.0,
        "value": 1.4925
      },
      {
        "year": 2019.0,
        "value": 1.47059
      },
      {
        "year": 2020.0,
        "value": 1.47058823529412
      },
      {
        "year": 2000.0,
        "value": 1.6949
      },
      {
        "year": 2005.0,
        "value": 1.5625
      },
      {
        "year": 2010.0,
        "value": 1.4925
      },
      {
        "year": 2015.0,
        "value": 1.4925
      },
      {
        "year": 2016.0,
        "value": 1.4925
      },
      {
        "year": 2017.0,
        "value": 1.4925
      },
      {
        "year": 2018.0,
        "value": 1.4925
      },
      {
        "year": 2019.0,
        "value": 1.47059
      },
      {
        "year": 2020.0,
        "value": 1.47058823529412
      }
    ],
    "targets": null
  },
  {
    "Name of international institution": "WTO",
    "Reporting Type": "G",
    "series": "SG_INT_MBRDEV",
    "goal": "10",
    "target": "10.6",
    "indicator": "10.6.1",
    "seriesDescription": "Proportion of members of developing countries in international organizations, by organization (%)",
    "values": [
      {
        "year": 2005.0,
        "value": 0.67114
      },
      {
        "year": 2010.0,
        "value": 0.65359
      },
      {
        "year": 2015.0,
        "value": 0.625
      },
      {
        "year": 2016.0,
        "value": 0.61728
      },
      {
        "year": 2017.0,
        "value": 0.60976
      },
      {
        "year": 2018.0,
        "value": 0.60976
      },
      {
        "year": 2019.0,
        "value": 0.60976
      },
      {
        "year": 2020.0,
        "value": 0.60976
      },
      {
        "year": 2021.0,
        "value": 0.60976
      },
      {
        "year": 2005.0,
        "value": 0.67114
      },
      {
        "year": 2010.0,
        "value": 0.65359
      },
      {
        "year": 2015.0,
        "value": 0.625
      },
      {
        "year": 2016.0,
        "value": 0.61728
      },
      {
        "year": 2017.0,
        "value": 0.60976
      },
      {
        "year": 2018.0,
        "value": 0.60976
      },
      {
        "year": 2019.0,
        "value": 0.60976
      },
      {
        "year": 2020.0,
        "value": 0.60976
      },
      {
        "year": 2021.0,
        "value": 0.60976
      }
    ],
    "targets": null
  },
  {
    "Name of international institution": "WTO",
    "Reporting Type": "G",
    "series": "SG_INT_MBRDEV",
    "goal": "16",
    "target": "16.8",
    "indicator": "16.8.1",
    "seriesDescription": "Proportion of members of developing countries in international organizations, by organization (%)",
    "values": [
      {
        "year": 2005.0,
        "value": 0.67114
      },
      {
        "year": 2010.0,
        "value": 0.65359
      },
      {
        "year": 2015.0,
        "value": 0.625
      },
      {
        "year": 2016.0,
        "value": 0.61728
      },
      {
        "year": 2017.0,
        "value": 0.60976
      },
      {
        "year": 2018.0,
        "value": 0.60976
      },
      {
        "year": 2019.0,
        "value": 0.60976
      },
      {
        "year": 2020.0,
        "value": 0.60976
      },
      {
        "year": 2021.0,
        "value": 0.60976
      },
      {
        "year": 2005.0,
        "value": 0.67114
      },
      {
        "year": 2010.0,
        "value": 0.65359
      },
      {
        "year": 2015.0,
        "value": 0.625
      },
      {
        "year": 2016.0,
        "value": 0.61728
      },
      {
        "year": 2017.0,
        "value": 0.60976
      },
      {
        "year": 2018.0,
        "value": 0.60976
      },
      {
        "year": 2019.0,
        "value": 0.60976
      },
      {
        "year": 2020.0,
        "value": 0.60976
      },
      {
        "year": 2021.0,
        "value": 0.60976
      }
    ],
    "targets": null
  },
  {
    "Name of international institution": "ADB",
    "Reporting Type": "G",
    "series": "SG_INT_VRTDEV",
    "goal": "10",
    "target": "10.6",
    "indicator": "10.6.1",
    "seriesDescription": "Proportion of voting rights of developing countries in international organizations, by organization (%)",
    "values": [
      {
        "year": 2000.0,
        "value": 1.226
      },
      {
        "year": 2005.0,
        "value": 1.191
      },
      {
        "year": 2010.0,
        "value": 1.288
      },
      {
        "year": 2015.0,
        "value": 1.171
      },
      {
        "year": 2016.0,
        "value": 1.17
      },
      {
        "year": 2017.0,
        "value": 1.17
      },
      {
        "year": 2018.0,
        "value": 1.1679
      },
      {
        "year": 2019.0,
        "value": 1.16351
      },
      {
        "year": 2020.0,
        "value": 1.164
      },
      {
        "year": 2000.0,
        "value": 1.226
      },
      {
        "year": 2005.0,
        "value": 1.191
      },
      {
        "year": 2010.0,
        "value": 1.288
      },
      {
        "year": 2015.0,
        "value": 1.171
      },
      {
        "year": 2016.0,
        "value": 1.17
      },
      {
        "year": 2017.0,
        "value": 1.17
      },
      {
        "year": 2018.0,
        "value": 1.1679
      },
      {
        "year": 2019.0,
        "value": 1.16351
      },
      {
        "year": 2020.0,
        "value": 1.164
      }
    ],
    "targets": null
  },
  {
    "Name of international institution": "ADB",
    "Reporting Type": "G",
    "series": "SG_INT_VRTDEV",
    "goal": "16",
    "target": "16.8",
    "indicator": "16.8.1",
    "seriesDescription": "Proportion of voting rights of developing countries in international organizations, by organization (%)",
    "values": [
      {
        "year": 2000.0,
        "value": 1.226
      },
      {
        "year": 2005.0,
        "value": 1.191
      },
      {
        "year": 2010.0,
        "value": 1.288
      },
      {
        "year": 2015.0,
        "value": 1.171
      },
      {
        "year": 2016.0,
        "value": 1.17
      },
      {
        "year": 2017.0,
        "value": 1.17
      },
      {
        "year": 2018.0,
        "value": 1.1679
      },
      {
        "year": 2019.0,
        "value": 1.16351
      },
      {
        "year": 2020.0,
        "value": 1.164
      },
      {
        "year": 2000.0,
        "value": 1.226
      },
      {
        "year": 2005.0,
        "value": 1.191
      },
      {
        "year": 2010.0,
        "value": 1.288
      },
      {
        "year": 2015.0,
        "value": 1.171
      },
      {
        "year": 2016.0,
        "value": 1.17
      },
      {
        "year": 2017.0,
        "value": 1.17
      },
      {
        "year": 2018.0,
        "value": 1.1679
      },
      {
        "year": 2019.0,
        "value": 1.16351
      },
      {
        "year": 2020.0,
        "value": 1.164
      }
    ],
    "targets": null
  },
  {
    "Name of international institution": "WTO",
    "Reporting Type": "G",
    "series": "SG_INT_VRTDEV",
    "goal": "10",
    "target": "10.6",
    "indicator": "10.6.1",
    "seriesDescription": "Proportion of voting rights of developing countries in international organizations, by organization (%)",
    "values": [
      {
        "year": 2005.0,
        "value": 0.6711
      },
      {
        "year": 2010.0,
        "value": 0.6536
      },
      {
        "year": 2015.0,
        "value": 0.625
      },
      {
        "year": 2016.0,
        "value": 0.6173
      },
      {
        "year": 2017.0,
        "value": 0.6098
      },
      {
        "year": 2018.0,
        "value": 0.6098
      },
      {
        "year": 2019.0,
        "value": 0.6098
      },
      {
        "year": 2020.0,
        "value": 0.60976
      },
      {
        "year": 2021.0,
        "value": 0.60976
      },
      {
        "year": 2005.0,
        "value": 0.6711
      },
      {
        "year": 2010.0,
        "value": 0.6536
      },
      {
        "year": 2015.0,
        "value": 0.625
      },
      {
        "year": 2016.0,
        "value": 0.6173
      },
      {
        "year": 2017.0,
        "value": 0.6098
      },
      {
        "year": 2018.0,
        "value": 0.6098
      },
      {
        "year": 2019.0,
        "value": 0.6098
      },
      {
        "year": 2020.0,
        "value": 0.60976
      },
      {
        "year": 2021.0,
        "value": 0.60976
      }
    ],
    "targets": null
  },
  {
    "Name of international institution": "WTO",
    "Reporting Type": "G",
    "series": "SG_INT_VRTDEV",
    "goal": "16",
    "target": "16.8",
    "indicator": "16.8.1",
    "seriesDescription": "Proportion of voting rights of developing countries in international organizations, by organization (%)",
    "values": [
      {
        "year": 2005.0,
        "value": 0.6711
      },
      {
        "year": 2010.0,
        "value": 0.6536
      },
      {
        "year": 2015.0,
        "value": 0.625
      },
      {
        "year": 2016.0,
        "value": 0.6173
      },
      {
        "year": 2017.0,
        "value": 0.6098
      },
      {
        "year": 2018.0,
        "value": 0.6098
      },
      {
        "year": 2019.0,
        "value": 0.6098
      },
      {
        "year": 2020.0,
        "value": 0.60976
      },
      {
        "year": 2021.0,
        "value": 0.60976
      },
      {
        "year": 2005.0,
        "value": 0.6711
      },
      {
        "year": 2010.0,
        "value": 0.6536
      },
      {
        "year": 2015.0,
        "value": 0.625
      },
      {
        "year": 2016.0,
        "value": 0.6173
      },
      {
        "year": 2017.0,
        "value": 0.6098
      },
      {
        "year": 2018.0,
        "value": 0.6098
      },
      {
        "year": 2019.0,
        "value": 0.6098
      },
      {
        "year": 2020.0,
        "value": 0.60976
      },
      {
        "year": 2021.0,
        "value": 0.60976
      }
    ],
    "targets": null
  },
  {
    "Reporting Type": "G",
    "series": "DC_TRF_TOTDL",
    "goal": "10",
    "target": "10.b",
    "indicator": "10.b.1",
    "seriesDescription": "Total assistance for development, by donor countries (millions of current United States dollars)",
    "values": [
      {
        "year": 2004.0,
        "value": 420.96
      },
      {
        "year": 2005.0,
        "value": 483.0
      },
      {
        "year": 2006.0,
        "value": 513.0
      },
      {
        "year": 2007.0,
        "value": 514.0
      },
      {
        "year": 2008.0,
        "value": 435.2
      },
      {
        "year": 2009.0,
        "value": 411.35
      },
      {
        "year": 2010.0,
        "value": 380.91
      },
      {
        "year": 2011.0,
        "value": 381.24
      },
      {
        "year": 2012.0,
        "value": 304.5
      },
      {
        "year": 2013.0,
        "value": 271.77
      },
      {
        "year": 2014.0,
        "value": 273.97
      },
      {
        "year": 2015.0,
        "value": 254.76
      },
      {
        "year": 2016.0,
        "value": 327.54
      },
      {
        "year": 2017.0,
        "value": 319.31
      },
      {
        "year": 2018.0,
        "value": 291.54
      },
      {
        "year": 2019.0,
        "value": 315.85
      },
      {
        "year": 2020.0,
        "value": 504.16
      },
      {
        "year": 2021.0,
        "value": 347.45
      }
    ],
    "targets": null
  },
  {
    "Reporting Type": "G",
    "Type of renewable technology": "ALL",
    "series": "EG_EGY_RNEW",
    "goal": "7",
    "target": "7.b",
    "indicator": "7.b.1",
    "seriesDescription": "Installed renewable\u00a0electricity-generating capacity (watts per capita)",
    "values": [
      {
        "year": 2000.0,
        "value": 94.924
      },
      {
        "year": 2001.0,
        "value": 98.586
      },
      {
        "year": 2002.0,
        "value": 103.022
      },
      {
        "year": 2003.0,
        "value": 101.384
      },
      {
        "year": 2004.0,
        "value": 101.341
      },
      {
        "year": 2005.0,
        "value": 102.001
      },
      {
        "year": 2006.0,
        "value": 105.414
      },
      {
        "year": 2007.0,
        "value": 109.374
      },
      {
        "year": 2008.0,
        "value": 112.6
      },
      {
        "year": 2009.0,
        "value": 117.672
      },
      {
        "year": 2010.0,
        "value": 124.461
      },
      {
        "year": 2011.0,
        "value": 132.659
      },
      {
        "year": 2012.0,
        "value": 140.47
      },
      {
        "year": 2013.0,
        "value": 149.492
      },
      {
        "year": 2014.0,
        "value": 159.648
      },
      {
        "year": 2015.0,
        "value": 170.432
      },
      {
        "year": 2016.0,
        "value": 186.765
      },
      {
        "year": 2017.0,
        "value": 208.834
      },
      {
        "year": 2018.0,
        "value": 250.331
      },
      {
        "year": 2019.0,
        "value": 314.637
      },
      {
        "year": 2020.0,
        "value": 384.538
      },
      {
        "year": 2000.0,
        "value": 94.924
      },
      {
        "year": 2001.0,
        "value": 98.586
      },
      {
        "year": 2002.0,
        "value": 103.022
      },
      {
        "year": 2003.0,
        "value": 101.384
      },
      {
        "year": 2004.0,
        "value": 101.341
      },
      {
        "year": 2005.0,
        "value": 102.001
      },
      {
        "year": 2006.0,
        "value": 105.414
      },
      {
        "year": 2007.0,
        "value": 109.374
      },
      {
        "year": 2008.0,
        "value": 112.6
      },
      {
        "year": 2009.0,
        "value": 117.672
      },
      {
        "year": 2010.0,
        "value": 124.461
      },
      {
        "year": 2011.0,
        "value": 132.659
      },
      {
        "year": 2012.0,
        "value": 140.47
      },
      {
        "year": 2013.0,
        "value": 149.492
      },
      {
        "year": 2014.0,
        "value": 159.648
      },
      {
        "year": 2015.0,
        "value": 170.432
      },
      {
        "year": 2016.0,
        "value": 186.765
      },
      {
        "year": 2017.0,
        "value": 208.834
      },
      {
        "year": 2018.0,
        "value": 250.331
      },
      {
        "year": 2019.0,
        "value": 314.637
      },
      {
        "year": 2020.0,
        "value": 384.538
      }
    ],
    "targets": null
  },
  {
    "Reporting Type": "G",
    "Type of renewable technology": "ALL",
    "series": "EG_EGY_RNEW",
    "goal": "12",
    "target": "12.a",
    "indicator": "12.a.1",
    "seriesDescription": "Installed renewable\u00a0electricity-generating capacity (watts per capita)",
    "values": [
      {
        "year": 2000.0,
        "value": 94.924
      },
      {
        "year": 2001.0,
        "value": 98.586
      },
      {
        "year": 2002.0,
        "value": 103.022
      },
      {
        "year": 2003.0,
        "value": 101.384
      },
      {
        "year": 2004.0,
        "value": 101.341
      },
      {
        "year": 2005.0,
        "value": 102.001
      },
      {
        "year": 2006.0,
        "value": 105.414
      },
      {
        "year": 2007.0,
        "value": 109.374
      },
      {
        "year": 2008.0,
        "value": 112.6
      },
      {
        "year": 2009.0,
        "value": 117.672
      },
      {
        "year": 2010.0,
        "value": 124.461
      },
      {
        "year": 2011.0,
        "value": 132.659
      },
      {
        "year": 2012.0,
        "value": 140.47
      },
      {
        "year": 2013.0,
        "value": 149.492
      },
      {
        "year": 2014.0,
        "value": 159.648
      },
      {
        "year": 2015.0,
        "value": 170.432
      },
      {
        "year": 2016.0,
        "value": 186.765
      },
      {
        "year": 2017.0,
        "value": 208.834
      },
      {
        "year": 2018.0,
        "value": 250.331
      },
      {
        "year": 2019.0,
        "value": 314.637
      },
      {
        "year": 2020.0,
        "value": 384.538
      },
      {
        "year": 2000.0,
        "value": 94.924
      },
      {
        "year": 2001.0,
        "value": 98.586
      },
      {
        "year": 2002.0,
        "value": 103.022
      },
      {
        "year": 2003.0,
        "value": 101.384
      },
      {
        "year": 2004.0,
        "value": 101.341
      },
      {
        "year": 2005.0,
        "value": 102.001
      },
      {
        "year": 2006.0,
        "value": 105.414
      },
      {
        "year": 2007.0,
        "value": 109.374
      },
      {
        "year": 2008.0,
        "value": 112.6
      },
      {
        "year": 2009.0,
        "value": 117.672
      },
      {
        "year": 2010.0,
        "value": 124.461
      },
      {
        "year": 2011.0,
        "value": 132.659
      },
      {
        "year": 2012.0,
        "value": 140.47
      },
      {
        "year": 2013.0,
        "value": 149.492
      },
      {
        "year": 2014.0,
        "value": 159.648
      },
      {
        "year": 2015.0,
        "value": 170.432
      },
      {
        "year": 2016.0,
        "value": 186.765
      },
      {
        "year": 2017.0,
        "value": 208.834
      },
      {
        "year": 2018.0,
        "value": 250.331
      },
      {
        "year": 2019.0,
        "value": 314.637
      },
      {
        "year": 2020.0,
        "value": 384.538
      }
    ],
    "targets": null
  },
  {
    "Reporting Type": "G",
    "Type of renewable technology": "WIND",
    "series": "EG_EGY_RNEW",
    "goal": "7",
    "target": "7.b",
    "indicator": "7.b.1",
    "seriesDescription": "Installed renewable\u00a0electricity-generating capacity (watts per capita)",
    "values": [
      {
        "year": 2000.0,
        "value": 0.118
      },
      {
        "year": 2001.0,
        "value": 0.226
      },
      {
        "year": 2002.0,
        "value": 0.382
      },
      {
        "year": 2003.0,
        "value": 0.379
      },
      {
        "year": 2004.0,
        "value": 0.377
      },
      {
        "year": 2005.0,
        "value": 1.053
      },
      {
        "year": 2006.0,
        "value": 4.469
      },
      {
        "year": 2007.0,
        "value": 8.113
      },
      {
        "year": 2008.0,
        "value": 10.878
      },
      {
        "year": 2009.0,
        "value": 16.2
      },
      {
        "year": 2010.0,
        "value": 20.524
      },
      {
        "year": 2011.0,
        "value": 22.464
      },
      {
        "year": 2012.0,
        "value": 24.457
      },
      {
        "year": 2013.0,
        "value": 26.224
      },
      {
        "year": 2014.0,
        "value": 27.124
      },
      {
        "year": 2015.0,
        "value": 27.452
      },
      {
        "year": 2016.0,
        "value": 28.876
      },
      {
        "year": 2017.0,
        "value": 29.247
      },
      {
        "year": 2018.0,
        "value": 30.059
      },
      {
        "year": 2019.0,
        "value": 35.552
      },
      {
        "year": 2020.0,
        "value": 35.844
      },
      {
        "year": 2000.0,
        "value": 0.118
      },
      {
        "year": 2001.0,
        "value": 0.226
      },
      {
        "year": 2002.0,
        "value": 0.382
      },
      {
        "year": 2003.0,
        "value": 0.379
      },
      {
        "year": 2004.0,
        "value": 0.377
      },
      {
        "year": 2005.0,
        "value": 1.053
      },
      {
        "year": 2006.0,
        "value": 4.469
      },
      {
        "year": 2007.0,
        "value": 8.113
      },
      {
        "year": 2008.0,
        "value": 10.878
      },
      {
        "year": 2009.0,
        "value": 16.2
      },
      {
        "year": 2010.0,
        "value": 20.524
      },
      {
        "year": 2011.0,
        "value": 22.464
      },
      {
        "year": 2012.0,
        "value": 24.457
      },
      {
        "year": 2013.0,
        "value": 26.224
      },
      {
        "year": 2014.0,
        "value": 27.124
      },
      {
        "year": 2015.0,
        "value": 27.452
      },
      {
        "year": 2016.0,
        "value": 28.876
      },
      {
        "year": 2017.0,
        "value": 29.247
      },
      {
        "year": 2018.0,
        "value": 30.059
      },
      {
        "year": 2019.0,
        "value": 35.552
      },
      {
        "year": 2020.0,
        "value": 35.844
      }
    ],
    "targets": null
  },
  {
    "Reporting Type": "G",
    "Type of renewable technology": "WIND",
    "series": "EG_EGY_RNEW",
    "goal": "12",
    "target": "12.a",
    "indicator": "12.a.1",
    "seriesDescription": "Installed renewable\u00a0electricity-generating capacity (watts per capita)",
    "values": [
      {
        "year": 2000.0,
        "value": 0.118
      },
      {
        "year": 2001.0,
        "value": 0.226
      },
      {
        "year": 2002.0,
        "value": 0.382
      },
      {
        "year": 2003.0,
        "value": 0.379
      },
      {
        "year": 2004.0,
        "value": 0.377
      },
      {
        "year": 2005.0,
        "value": 1.053
      },
      {
        "year": 2006.0,
        "value": 4.469
      },
      {
        "year": 2007.0,
        "value": 8.113
      },
      {
        "year": 2008.0,
        "value": 10.878
      },
      {
        "year": 2009.0,
        "value": 16.2
      },
      {
        "year": 2010.0,
        "value": 20.524
      },
      {
        "year": 2011.0,
        "value": 22.464
      },
      {
        "year": 2012.0,
        "value": 24.457
      },
      {
        "year": 2013.0,
        "value": 26.224
      },
      {
        "year": 2014.0,
        "value": 27.124
      },
      {
        "year": 2015.0,
        "value": 27.452
      },
      {
        "year": 2016.0,
        "value": 28.876
      },
      {
        "year": 2017.0,
        "value": 29.247
      },
      {
        "year": 2018.0,
        "value": 30.059
      },
      {
        "year": 2019.0,
        "value": 35.552
      },
      {
        "year": 2020.0,
        "value": 35.844
      },
      {
        "year": 2000.0,
        "value": 0.118
      },
      {
        "year": 2001.0,
        "value": 0.226
      },
      {
        "year": 2002.0,
        "value": 0.382
      },
      {
        "year": 2003.0,
        "value": 0.379
      },
      {
        "year": 2004.0,
        "value": 0.377
      },
      {
        "year": 2005.0,
        "value": 1.053
      },
      {
        "year": 2006.0,
        "value": 4.469
      },
      {
        "year": 2007.0,
        "value": 8.113
      },
      {
        "year": 2008.0,
        "value": 10.878
      },
      {
        "year": 2009.0,
        "value": 16.2
      },
      {
        "year": 2010.0,
        "value": 20.524
      },
      {
        "year": 2011.0,
        "value": 22.464
      },
      {
        "year": 2012.0,
        "value": 24.457
      },
      {
        "year": 2013.0,
        "value": 26.224
      },
      {
        "year": 2014.0,
        "value": 27.124
      },
      {
        "year": 2015.0,
        "value": 27.452
      },
      {
        "year": 2016.0,
        "value": 28.876
      },
      {
        "year": 2017.0,
        "value": 29.247
      },
      {
        "year": 2018.0,
        "value": 30.059
      },
      {
        "year": 2019.0,
        "value": 35.552
      },
      {
        "year": 2020.0,
        "value": 35.844
      }
    ],
    "targets": null
  },
  {
    "Reporting Type": "G",
    "Type of renewable technology": "SOLAR",
    "series": "EG_EGY_RNEW",
    "goal": "7",
    "target": "7.b",
    "indicator": "7.b.1",
    "seriesDescription": "Installed renewable\u00a0electricity-generating capacity (watts per capita)",
    "values": [
      {
        "year": 2000.0,
        "value": 0.005
      },
      {
        "year": 2001.0,
        "value": 0.009
      },
      {
        "year": 2002.0,
        "value": 0.013
      },
      {
        "year": 2003.0,
        "value": 0.022
      },
      {
        "year": 2004.0,
        "value": 0.027
      },
      {
        "year": 2005.0,
        "value": 0.044
      },
      {
        "year": 2006.0,
        "value": 0.061
      },
      {
        "year": 2007.0,
        "value": 0.105
      },
      {
        "year": 2008.0,
        "value": 0.243
      },
      {
        "year": 2009.0,
        "value": 0.411
      },
      {
        "year": 2010.0,
        "value": 1.492
      },
      {
        "year": 2011.0,
        "value": 5.583
      },
      {
        "year": 2012.0,
        "value": 9.907
      },
      {
        "year": 2013.0,
        "value": 17.501
      },
      {
        "year": 2014.0,
        "value": 27.073
      },
      {
        "year": 2015.0,
        "value": 37.538
      },
      {
        "year": 2016.0,
        "value": 52.718
      },
      {
        "year": 2017.0,
        "value": 74.667
      },
      {
        "year": 2018.0,
        "value": 115.403
      },
      {
        "year": 2019.0,
        "value": 174.54
      },
      {
        "year": 2020.0,
        "value": 244.248
      },
      {
        "year": 2000.0,
        "value": 0.005
      },
      {
        "year": 2001.0,
        "value": 0.009
      },
      {
        "year": 2002.0,
        "value": 0.013
      },
      {
        "year": 2003.0,
        "value": 0.022
      },
      {
        "year": 2004.0,
        "value": 0.027
      },
      {
        "year": 2005.0,
        "value": 0.044
      },
      {
        "year": 2006.0,
        "value": 0.061
      },
      {
        "year": 2007.0,
        "value": 0.105
      },
      {
        "year": 2008.0,
        "value": 0.243
      },
      {
        "year": 2009.0,
        "value": 0.411
      },
      {
        "year": 2010.0,
        "value": 1.492
      },
      {
        "year": 2011.0,
        "value": 5.583
      },
      {
        "year": 2012.0,
        "value": 9.907
      },
      {
        "year": 2013.0,
        "value": 17.501
      },
      {
        "year": 2014.0,
        "value": 27.073
      },
      {
        "year": 2015.0,
        "value": 37.538
      },
      {
        "year": 2016.0,
        "value": 52.718
      },
      {
        "year": 2017.0,
        "value": 74.667
      },
      {
        "year": 2018.0,
        "value": 115.403
      },
      {
        "year": 2019.0,
        "value": 174.54
      },
      {
        "year": 2020.0,
        "value": 244.248
      }
    ],
    "targets": null
  },
  {
    "Reporting Type": "G",
    "Type of renewable technology": "SOLAR",
    "series": "EG_EGY_RNEW",
    "goal": "12",
    "target": "12.a",
    "indicator": "12.a.1",
    "seriesDescription": "Installed renewable\u00a0electricity-generating capacity (watts per capita)",
    "values": [
      {
        "year": 2000.0,
        "value": 0.005
      },
      {
        "year": 2001.0,
        "value": 0.009
      },
      {
        "year": 2002.0,
        "value": 0.013
      },
      {
        "year": 2003.0,
        "value": 0.022
      },
      {
        "year": 2004.0,
        "value": 0.027
      },
      {
        "year": 2005.0,
        "value": 0.044
      },
      {
        "year": 2006.0,
        "value": 0.061
      },
      {
        "year": 2007.0,
        "value": 0.105
      },
      {
        "year": 2008.0,
        "value": 0.243
      },
      {
        "year": 2009.0,
        "value": 0.411
      },
      {
        "year": 2010.0,
        "value": 1.492
      },
      {
        "year": 2011.0,
        "value": 5.583
      },
      {
        "year": 2012.0,
        "value": 9.907
      },
      {
        "year": 2013.0,
        "value": 17.501
      },
      {
        "year": 2014.0,
        "value": 27.073
      },
      {
        "year": 2015.0,
        "value": 37.538
      },
      {
        "year": 2016.0,
        "value": 52.718
      },
      {
        "year": 2017.0,
        "value": 74.667
      },
      {
        "year": 2018.0,
        "value": 115.403
      },
      {
        "year": 2019.0,
        "value": 174.54
      },
      {
        "year": 2020.0,
        "value": 244.248
      },
      {
        "year": 2000.0,
        "value": 0.005
      },
      {
        "year": 2001.0,
        "value": 0.009
      },
      {
        "year": 2002.0,
        "value": 0.013
      },
      {
        "year": 2003.0,
        "value": 0.022
      },
      {
        "year": 2004.0,
        "value": 0.027
      },
      {
        "year": 2005.0,
        "value": 0.044
      },
      {
        "year": 2006.0,
        "value": 0.061
      },
      {
        "year": 2007.0,
        "value": 0.105
      },
      {
        "year": 2008.0,
        "value": 0.243
      },
      {
        "year": 2009.0,
        "value": 0.411
      },
      {
        "year": 2010.0,
        "value": 1.492
      },
      {
        "year": 2011.0,
        "value": 5.583
      },
      {
        "year": 2012.0,
        "value": 9.907
      },
      {
        "year": 2013.0,
        "value": 17.501
      },
      {
        "year": 2014.0,
        "value": 27.073
      },
      {
        "year": 2015.0,
        "value": 37.538
      },
      {
        "year": 2016.0,
        "value": 52.718
      },
      {
        "year": 2017.0,
        "value": 74.667
      },
      {
        "year": 2018.0,
        "value": 115.403
      },
      {
        "year": 2019.0,
        "value": 174.54
      },
      {
        "year": 2020.0,
        "value": 244.248
      }
    ],
    "targets": null
  },
  {
    "Reporting Type": "G",
    "Type of renewable technology": "HYDROPOWER",
    "series": "EG_EGY_RNEW",
    "goal": "7",
    "target": "7.b",
    "indicator": "7.b.1",
    "seriesDescription": "Installed renewable\u00a0electricity-generating capacity (watts per capita)",
    "values": [
      {
        "year": 2000.0,
        "value": 82.853
      },
      {
        "year": 2001.0,
        "value": 82.32
      },
      {
        "year": 2002.0,
        "value": 85.741
      },
      {
        "year": 2003.0,
        "value": 85.139
      },
      {
        "year": 2004.0,
        "value": 84.611
      },
      {
        "year": 2005.0,
        "value": 84.107
      },
      {
        "year": 2006.0,
        "value": 83.671
      },
      {
        "year": 2007.0,
        "value": 83.796
      },
      {
        "year": 2008.0,
        "value": 84.187
      },
      {
        "year": 2009.0,
        "value": 83.832
      },
      {
        "year": 2010.0,
        "value": 85.279
      },
      {
        "year": 2011.0,
        "value": 87.701
      },
      {
        "year": 2012.0,
        "value": 89.151
      },
      {
        "year": 2013.0,
        "value": 88.867
      },
      {
        "year": 2014.0,
        "value": 88.6
      },
      {
        "year": 2015.0,
        "value": 88.694
      },
      {
        "year": 2016.0,
        "value": 88.466
      },
      {
        "year": 2017.0,
        "value": 88.255
      },
      {
        "year": 2018.0,
        "value": 88.155
      },
      {
        "year": 2019.0,
        "value": 88.021
      },
      {
        "year": 2020.0,
        "value": 87.896
      },
      {
        "year": 2000.0,
        "value": 82.853
      },
      {
        "year": 2001.0,
        "value": 82.32
      },
      {
        "year": 2002.0,
        "value": 85.741
      },
      {
        "year": 2003.0,
        "value": 85.139
      },
      {
        "year": 2004.0,
        "value": 84.611
      },
      {
        "year": 2005.0,
        "value": 84.107
      },
      {
        "year": 2006.0,
        "value": 83.671
      },
      {
        "year": 2007.0,
        "value": 83.796
      },
      {
        "year": 2008.0,
        "value": 84.187
      },
      {
        "year": 2009.0,
        "value": 83.832
      },
      {
        "year": 2010.0,
        "value": 85.279
      },
      {
        "year": 2011.0,
        "value": 87.701
      },
      {
        "year": 2012.0,
        "value": 89.151
      },
      {
        "year": 2013.0,
        "value": 88.867
      },
      {
        "year": 2014.0,
        "value": 88.6
      },
      {
        "year": 2015.0,
        "value": 88.694
      },
      {
        "year": 2016.0,
        "value": 88.466
      },
      {
        "year": 2017.0,
        "value": 88.255
      },
      {
        "year": 2018.0,
        "value": 88.155
      },
      {
        "year": 2019.0,
        "value": 88.021
      },
      {
        "year": 2020.0,
        "value": 87.896
      }
    ],
    "targets": null
  },
  {
    "Reporting Type": "G",
    "Type of renewable technology": "HYDROPOWER",
    "series": "EG_EGY_RNEW",
    "goal": "12",
    "target": "12.a",
    "indicator": "12.a.1",
    "seriesDescription": "Installed renewable\u00a0electricity-generating capacity (watts per capita)",
    "values": [
      {
        "year": 2000.0,
        "value": 82.853
      },
      {
        "year": 2001.0,
        "value": 82.32
      },
      {
        "year": 2002.0,
        "value": 85.741
      },
      {
        "year": 2003.0,
        "value": 85.139
      },
      {
        "year": 2004.0,
        "value": 84.611
      },
      {
        "year": 2005.0,
        "value": 84.107
      },
      {
        "year": 2006.0,
        "value": 83.671
      },
      {
        "year": 2007.0,
        "value": 83.796
      },
      {
        "year": 2008.0,
        "value": 84.187
      },
      {
        "year": 2009.0,
        "value": 83.832
      },
      {
        "year": 2010.0,
        "value": 85.279
      },
      {
        "year": 2011.0,
        "value": 87.701
      },
      {
        "year": 2012.0,
        "value": 89.151
      },
      {
        "year": 2013.0,
        "value": 88.867
      },
      {
        "year": 2014.0,
        "value": 88.6
      },
      {
        "year": 2015.0,
        "value": 88.694
      },
      {
        "year": 2016.0,
        "value": 88.466
      },
      {
        "year": 2017.0,
        "value": 88.255
      },
      {
        "year": 2018.0,
        "value": 88.155
      },
      {
        "year": 2019.0,
        "value": 88.021
      },
      {
        "year": 2020.0,
        "value": 87.896
      },
      {
        "year": 2000.0,
        "value": 82.853
      },
      {
        "year": 2001.0,
        "value": 82.32
      },
      {
        "year": 2002.0,
        "value": 85.741
      },
      {
        "year": 2003.0,
        "value": 85.139
      },
      {
        "year": 2004.0,
        "value": 84.611
      },
      {
        "year": 2005.0,
        "value": 84.107
      },
      {
        "year": 2006.0,
        "value": 83.671
      },
      {
        "year": 2007.0,
        "value": 83.796
      },
      {
        "year": 2008.0,
        "value": 84.187
      },
      {
        "year": 2009.0,
        "value": 83.832
      },
      {
        "year": 2010.0,
        "value": 85.279
      },
      {
        "year": 2011.0,
        "value": 87.701
      },
      {
        "year": 2012.0,
        "value": 89.151
      },
      {
        "year": 2013.0,
        "value": 88.867
      },
      {
        "year": 2014.0,
        "value": 88.6
      },
      {
        "year": 2015.0,
        "value": 88.694
      },
      {
        "year": 2016.0,
        "value": 88.466
      },
      {
        "year": 2017.0,
        "value": 88.255
      },
      {
        "year": 2018.0,
        "value": 88.155
      },
      {
        "year": 2019.0,
        "value": 88.021
      },
      {
        "year": 2020.0,
        "value": 87.896
      }
    ],
    "targets": null
  },
  {
    "Reporting Type": "G",
    "Type of renewable technology": "GEOTHERMAL",
    "series": "EG_EGY_RNEW",
    "goal": "7",
    "target": "7.b",
    "indicator": "7.b.1",
    "seriesDescription": "Installed renewable\u00a0electricity-generating capacity (watts per capita)",
    "values": [
      {
        "year": 2000.0,
        "value": 0.0
      },
      {
        "year": 2001.0,
        "value": 0.0
      },
      {
        "year": 2002.0,
        "value": 0.0
      },
      {
        "year": 2003.0,
        "value": 0.0
      },
      {
        "year": 2004.0,
        "value": 0.0
      },
      {
        "year": 2005.0,
        "value": 0.0
      },
      {
        "year": 2006.0,
        "value": 0.0
      },
      {
        "year": 2007.0,
        "value": 0.0
      },
      {
        "year": 2008.0,
        "value": 0.0
      },
      {
        "year": 2009.0,
        "value": 0.0
      },
      {
        "year": 2010.0,
        "value": 0.0
      },
      {
        "year": 2011.0,
        "value": 0.0
      },
      {
        "year": 2012.0,
        "value": 0.0
      },
      {
        "year": 2013.0,
        "value": 0.0
      },
      {
        "year": 2014.0,
        "value": 0.0
      },
      {
        "year": 2015.0,
        "value": 0.0
      },
      {
        "year": 2016.0,
        "value": 0.0
      },
      {
        "year": 2017.0,
        "value": 0.0
      },
      {
        "year": 2018.0,
        "value": 0.001
      },
      {
        "year": 2019.0,
        "value": 0.013
      },
      {
        "year": 2020.0,
        "value": 0.013
      },
      {
        "year": 2000.0,
        "value": 0.0
      },
      {
        "year": 2001.0,
        "value": 0.0
      },
      {
        "year": 2002.0,
        "value": 0.0
      },
      {
        "year": 2003.0,
        "value": 0.0
      },
      {
        "year": 2004.0,
        "value": 0.0
      },
      {
        "year": 2005.0,
        "value": 0.0
      },
      {
        "year": 2006.0,
        "value": 0.0
      },
      {
        "year": 2007.0,
        "value": 0.0
      },
      {
        "year": 2008.0,
        "value": 0.0
      },
      {
        "year": 2009.0,
        "value": 0.0
      },
      {
        "year": 2010.0,
        "value": 0.0
      },
      {
        "year": 2011.0,
        "value": 0.0
      },
      {
        "year": 2012.0,
        "value": 0.0
      },
      {
        "year": 2013.0,
        "value": 0.0
      },
      {
        "year": 2014.0,
        "value": 0.0
      },
      {
        "year": 2015.0,
        "value": 0.0
      },
      {
        "year": 2016.0,
        "value": 0.0
      },
      {
        "year": 2017.0,
        "value": 0.0
      },
      {
        "year": 2018.0,
        "value": 0.001
      },
      {
        "year": 2019.0,
        "value": 0.013
      },
      {
        "year": 2020.0,
        "value": 0.013
      }
    ],
    "targets": null
  },
  {
    "Reporting Type": "G",
    "Type of renewable technology": "GEOTHERMAL",
    "series": "EG_EGY_RNEW",
    "goal": "12",
    "target": "12.a",
    "indicator": "12.a.1",
    "seriesDescription": "Installed renewable\u00a0electricity-generating capacity (watts per capita)",
    "values": [
      {
        "year": 2000.0,
        "value": 0.0
      },
      {
        "year": 2001.0,
        "value": 0.0
      },
      {
        "year": 2002.0,
        "value": 0.0
      },
      {
        "year": 2003.0,
        "value": 0.0
      },
      {
        "year": 2004.0,
        "value": 0.0
      },
      {
        "year": 2005.0,
        "value": 0.0
      },
      {
        "year": 2006.0,
        "value": 0.0
      },
      {
        "year": 2007.0,
        "value": 0.0
      },
      {
        "year": 2008.0,
        "value": 0.0
      },
      {
        "year": 2009.0,
        "value": 0.0
      },
      {
        "year": 2010.0,
        "value": 0.0
      },
      {
        "year": 2011.0,
        "value": 0.0
      },
      {
        "year": 2012.0,
        "value": 0.0
      },
      {
        "year": 2013.0,
        "value": 0.0
      },
      {
        "year": 2014.0,
        "value": 0.0
      },
      {
        "year": 2015.0,
        "value": 0.0
      },
      {
        "year": 2016.0,
        "value": 0.0
      },
      {
        "year": 2017.0,
        "value": 0.0
      },
      {
        "year": 2018.0,
        "value": 0.001
      },
      {
        "year": 2019.0,
        "value": 0.013
      },
      {
        "year": 2020.0,
        "value": 0.013
      },
      {
        "year": 2000.0,
        "value": 0.0
      },
      {
        "year": 2001.0,
        "value": 0.0
      },
      {
        "year": 2002.0,
        "value": 0.0
      },
      {
        "year": 2003.0,
        "value": 0.0
      },
      {
        "year": 2004.0,
        "value": 0.0
      },
      {
        "year": 2005.0,
        "value": 0.0
      },
      {
        "year": 2006.0,
        "value": 0.0
      },
      {
        "year": 2007.0,
        "value": 0.0
      },
      {
        "year": 2008.0,
        "value": 0.0
      },
      {
        "year": 2009.0,
        "value": 0.0
      },
      {
        "year": 2010.0,
        "value": 0.0
      },
      {
        "year": 2011.0,
        "value": 0.0
      },
      {
        "year": 2012.0,
        "value": 0.0
      },
      {
        "year": 2013.0,
        "value": 0.0
      },
      {
        "year": 2014.0,
        "value": 0.0
      },
      {
        "year": 2015.0,
        "value": 0.0
      },
      {
        "year": 2016.0,
        "value": 0.0
      },
      {
        "year": 2017.0,
        "value": 0.0
      },
      {
        "year": 2018.0,
        "value": 0.001
      },
      {
        "year": 2019.0,
        "value": 0.013
      },
      {
        "year": 2020.0,
        "value": 0.013
      }
    ],
    "targets": null
  },
  {
    "Reporting Type": "G",
    "Type of renewable technology": "BIOENERGY",
    "series": "EG_EGY_RNEW",
    "goal": "7",
    "target": "7.b",
    "indicator": "7.b.1",
    "seriesDescription": "Installed renewable\u00a0electricity-generating capacity (watts per capita)",
    "values": [
      {
        "year": 2000.0,
        "value": 11.948
      },
      {
        "year": 2001.0,
        "value": 16.03
      },
      {
        "year": 2002.0,
        "value": 16.885
      },
      {
        "year": 2003.0,
        "value": 15.843
      },
      {
        "year": 2004.0,
        "value": 16.327
      },
      {
        "year": 2005.0,
        "value": 16.798
      },
      {
        "year": 2006.0,
        "value": 17.212
      },
      {
        "year": 2007.0,
        "value": 17.361
      },
      {
        "year": 2008.0,
        "value": 17.292
      },
      {
        "year": 2009.0,
        "value": 17.228
      },
      {
        "year": 2010.0,
        "value": 17.167
      },
      {
        "year": 2011.0,
        "value": 16.911
      },
      {
        "year": 2012.0,
        "value": 16.955
      },
      {
        "year": 2013.0,
        "value": 16.901
      },
      {
        "year": 2014.0,
        "value": 16.85
      },
      {
        "year": 2015.0,
        "value": 16.748
      },
      {
        "year": 2016.0,
        "value": 16.705
      },
      {
        "year": 2017.0,
        "value": 16.666
      },
      {
        "year": 2018.0,
        "value": 16.713
      },
      {
        "year": 2019.0,
        "value": 16.512
      },
      {
        "year": 2020.0,
        "value": 16.537
      },
      {
        "year": 2000.0,
        "value": 11.948
      },
      {
        "year": 2001.0,
        "value": 16.03
      },
      {
        "year": 2002.0,
        "value": 16.885
      },
      {
        "year": 2003.0,
        "value": 15.843
      },
      {
        "year": 2004.0,
        "value": 16.327
      },
      {
        "year": 2005.0,
        "value": 16.798
      },
      {
        "year": 2006.0,
        "value": 17.212
      },
      {
        "year": 2007.0,
        "value": 17.361
      },
      {
        "year": 2008.0,
        "value": 17.292
      },
      {
        "year": 2009.0,
        "value": 17.228
      },
      {
        "year": 2010.0,
        "value": 17.167
      },
      {
        "year": 2011.0,
        "value": 16.911
      },
      {
        "year": 2012.0,
        "value": 16.955
      },
      {
        "year": 2013.0,
        "value": 16.901
      },
      {
        "year": 2014.0,
        "value": 16.85
      },
      {
        "year": 2015.0,
        "value": 16.748
      },
      {
        "year": 2016.0,
        "value": 16.705
      },
      {
        "year": 2017.0,
        "value": 16.666
      },
      {
        "year": 2018.0,
        "value": 16.713
      },
      {
        "year": 2019.0,
        "value": 16.512
      },
      {
        "year": 2020.0,
        "value": 16.537
      }
    ],
    "targets": null
  },
  {
    "Reporting Type": "G",
    "Type of renewable technology": "BIOENERGY",
    "series": "EG_EGY_RNEW",
    "goal": "12",
    "target": "12.a",
    "indicator": "12.a.1",
    "seriesDescription": "Installed renewable\u00a0electricity-generating capacity (watts per capita)",
    "values": [
      {
        "year": 2000.0,
        "value": 11.948
      },
      {
        "year": 2001.0,
        "value": 16.03
      },
      {
        "year": 2002.0,
        "value": 16.885
      },
      {
        "year": 2003.0,
        "value": 15.843
      },
      {
        "year": 2004.0,
        "value": 16.327
      },
      {
        "year": 2005.0,
        "value": 16.798
      },
      {
        "year": 2006.0,
        "value": 17.212
      },
      {
        "year": 2007.0,
        "value": 17.361
      },
      {
        "year": 2008.0,
        "value": 17.292
      },
      {
        "year": 2009.0,
        "value": 17.228
      },
      {
        "year": 2010.0,
        "value": 17.167
      },
      {
        "year": 2011.0,
        "value": 16.911
      },
      {
        "year": 2012.0,
        "value": 16.955
      },
      {
        "year": 2013.0,
        "value": 16.901
      },
      {
        "year": 2014.0,
        "value": 16.85
      },
      {
        "year": 2015.0,
        "value": 16.748
      },
      {
        "year": 2016.0,
        "value": 16.705
      },
      {
        "year": 2017.0,
        "value": 16.666
      },
      {
        "year": 2018.0,
        "value": 16.713
      },
      {
        "year": 2019.0,
        "value": 16.512
      },
      {
        "year": 2020.0,
        "value": 16.537
      },
      {
        "year": 2000.0,
        "value": 11.948
      },
      {
        "year": 2001.0,
        "value": 16.03
      },
      {
        "year": 2002.0,
        "value": 16.885
      },
      {
        "year": 2003.0,
        "value": 15.843
      },
      {
        "year": 2004.0,
        "value": 16.327
      },
      {
        "year": 2005.0,
        "value": 16.798
      },
      {
        "year": 2006.0,
        "value": 17.212
      },
      {
        "year": 2007.0,
        "value": 17.361
      },
      {
        "year": 2008.0,
        "value": 17.292
      },
      {
        "year": 2009.0,
        "value": 17.228
      },
      {
        "year": 2010.0,
        "value": 17.167
      },
      {
        "year": 2011.0,
        "value": 16.911
      },
      {
        "year": 2012.0,
        "value": 16.955
      },
      {
        "year": 2013.0,
        "value": 16.901
      },
      {
        "year": 2014.0,
        "value": 16.85
      },
      {
        "year": 2015.0,
        "value": 16.748
      },
      {
        "year": 2016.0,
        "value": 16.705
      },
      {
        "year": 2017.0,
        "value": 16.666
      },
      {
        "year": 2018.0,
        "value": 16.713
      },
      {
        "year": 2019.0,
        "value": 16.512
      },
      {
        "year": 2020.0,
        "value": 16.537
      }
    ],
    "targets": null
  },
  {
    "Sex": "BOTHSEX",
    "Reporting Type": "G",
    "series": "VC_IHR_PSRC",
    "goal": "16",
    "target": "16.1",
    "indicator": "16.1.1",
    "seriesDescription": "Number of victims of intentional homicide per 100,000 population, by sex (victims per 100,000 population)",
    "values": [
      {
        "year": 2001.0,
        "value": 1.38
      },
      {
        "year": 2006.0,
        "value": 1.0
      },
      {
        "year": 2007.0,
        "value": 0.77
      },
      {
        "year": 2008.0,
        "value": 0.83
      },
      {
        "year": 2009.0,
        "value": 0.78
      },
      {
        "year": 2010.0,
        "value": 0.77
      },
      {
        "year": 2012.0,
        "value": 0.77
      },
      {
        "year": 2013.0,
        "value": 0.72
      },
      {
        "year": 2015.0,
        "value": 0.82
      }
    ],
    "targets": {
      "targetValue": 1,
      "type": "min"
    }
  },
  {
    "Sex": "BOTHSEX",
    "Reporting Type": "G",
    "series": "VC_IHR_PSRCN",
    "goal": "16",
    "target": "16.1",
    "indicator": "16.1.1",
    "seriesDescription": "Number of victims of intentional homicide, by sex (number)",
    "values": [
      {
        "year": 2001.0,
        "value": 306.0
      },
      {
        "year": 2006.0,
        "value": 228.0
      },
      {
        "year": 2007.0,
        "value": 176.0
      },
      {
        "year": 2008.0,
        "value": 191.0
      },
      {
        "year": 2009.0,
        "value": 181.0
      },
      {
        "year": 2010.0,
        "value": 179.0
      },
      {
        "year": 2012.0,
        "value": 179.0
      },
      {
        "year": 2013.0,
        "value": 168.0
      },
      {
        "year": 2015.0,
        "value": 192.0
      }
    ],
    "targets": {
      "targetValue": 1,
      "type": "min"
    }
  },
  {
    "Age": "ALLAGE",
    "Sex": "MALE",
    "series": "VC_HTF_DETVFL",
    "goal": "16",
    "target": "16.2",
    "indicator": "16.2.2",
    "seriesDescription": "Detected victims of human trafficking for forced labour, servitude and slavery, by age and sex (number)",
    "values": [
      {
        "year": 2011.0,
        "value": 10.0
      },
      {
        "year": 2012.0,
        "value": 66.0
      },
      {
        "year": 2013.0,
        "value": 57.0
      },
      {
        "year": 2014.0,
        "value": 52.0
      },
      {
        "year": 2015.0,
        "value": 64.0
      },
      {
        "year": 2016.0,
        "value": 64.0
      }
    ],
    "targets": null
  },
  {
    "Age": "ALLAGE",
    "Sex": "FEMALE",
    "series": "VC_HTF_DETVFL",
    "goal": "16",
    "target": "16.2",
    "indicator": "16.2.2",
    "seriesDescription": "Detected victims of human trafficking for forced labour, servitude and slavery, by age and sex (number)",
    "values": [
      {
        "year": 2011.0,
        "value": 84.0
      },
      {
        "year": 2012.0,
        "value": 244.0
      },
      {
        "year": 2013.0,
        "value": 198.0
      },
      {
        "year": 2014.0,
        "value": 154.0
      },
      {
        "year": 2015.0,
        "value": 122.0
      },
      {
        "year": 2016.0,
        "value": 52.0
      }
    ],
    "targets": null
  },
  {
    "Age": "ALLAGE",
    "Sex": "BOTHSEX",
    "Reporting Type": "G",
    "series": "VC_HTF_DETV",
    "goal": "16",
    "target": "16.2",
    "indicator": "16.2.2",
    "seriesDescription": "Detected victims of human trafficking, by age and sex (number)",
    "values": [
      {
        "year": 2008.0,
        "value": 106.0
      },
      {
        "year": 2009.0,
        "value": 329.0
      },
      {
        "year": 2010.0,
        "value": 319.0
      },
      {
        "year": 2011.0,
        "value": 131.0
      },
      {
        "year": 2012.0,
        "value": 462.0
      },
      {
        "year": 2014.0,
        "value": 292.0
      },
      {
        "year": 2015.0,
        "value": 192.0
      },
      {
        "year": 2016.0,
        "value": 156.0
      }
    ],
    "targets": null
  },
  {
    "Sex": "BOTHSEX",
    "Reporting Type": "G",
    "series": "VC_PRS_UNSNT",
    "goal": "16",
    "target": "16.3",
    "indicator": "16.3.2",
    "seriesDescription": "Unsentenced detainees as a proportion of overall prison population (%)",
    "values": [
      {
        "year": 2005.0,
        "value": 10.58
      },
      {
        "year": 2010.0,
        "value": 7.68
      },
      {
        "year": 2014.0,
        "value": 5.16
      },
      {
        "year": 2015.0,
        "value": 5.9
      },
      {
        "year": 2017.0,
        "value": 5.2
      },
      {
        "year": 2018.0,
        "value": 5.2
      }
    ],
    "targets": {
      "targetValue": 15,
      "type": "min"
    }
  },
  {
    "Sex": "BOTHSEX",
    "Reporting Type": "G",
    "series": "IU_COR_BRIB",
    "goal": "16",
    "target": "16.5",
    "indicator": "16.5.1",
    "seriesDescription": "Prevalence rate of bribery, by sex (%)",
    "values": [
      {
        "year": 2016.0,
        "value": 6.0
      },
      {
        "year": 2020.0,
        "value": 17.0
      }
    ],
    "targets": null
  },
  {
    "Reporting Type": "G",
    "series": "SG_PLN_PRVRIMON",
    "goal": "17",
    "target": "17.15",
    "indicator": "17.15.1",
    "seriesDescription": "Proportion of results indicators which will be monitored using government sources and monitoring systems - data by provider (%)",
    "values": [
      {
        "year": 2016.0,
        "value": 100.0
      }
    ],
    "targets": null
  },
  {
    "Reporting Type": "G",
    "series": "SG_PLN_PRVNDI",
    "goal": "17",
    "target": "17.15",
    "indicator": "17.15.1",
    "seriesDescription": "Proportion of project objectives of new development interventions drawn from country-led result frameworks - data by provider (%)",
    "values": [
      {
        "year": 2016.0,
        "value": 100.0
      }
    ],
    "targets": null
  },
  {
    "Reporting Type": "G",
    "series": "SG_PLN_PRVRICTRY",
    "goal": "17",
    "target": "17.15",
    "indicator": "17.15.1",
    "seriesDescription": "Proportion of results indicators drawn from country-led results frameworks - data by provider (%)",
    "values": [
      {
        "year": 2016.0,
        "value": 100.0
      }
    ],
    "targets": null
  },
  {
    "Reporting Type": "G",
    "series": "SG_PLN_PRPOLRES",
    "goal": "17",
    "target": "17.15",
    "indicator": "17.15.1",
    "seriesDescription": "Extent of use of country-owned results frameworks and planning tools by providers of development cooperation - data by provider (%) ",
    "values": [
      {
        "year": 2016.0,
        "value": 100.0
      }
    ],
    "targets": null
  },
  {
    "Reporting Type": "G",
    "series": "SG_PLN_MSTKSDG_P",
    "goal": "17",
    "target": "17.16",
    "indicator": "17.16.1",
    "seriesDescription": "Number of countries reporting progress in multi-stakeholder development effectiveness monitoring frameworks that support the achievement of the sustainable development goals, Provider (1 = YES; 0 = NO)",
    "values": [
      {
        "year": 2016.0,
        "value": 1.0
      }
    ],
    "targets": null
  },
  {
    "Reporting Type": "G",
    "series": "GF_FRN_FDI",
    "goal": "17",
    "target": "17.3",
    "indicator": "17.3.1",
    "seriesDescription": "Foreign direct investment (FDI) inflows (millions of US dollars)",
    "values": [
      {
        "year": 2000.0,
        "value": 4928.0
      },
      {
        "year": 2001.0,
        "value": 4109.0
      },
      {
        "year": 2002.0,
        "value": 1445.0
      },
      {
        "year": 2003.0,
        "value": 453.0
      },
      {
        "year": 2004.0,
        "value": 1898.0
      },
      {
        "year": 2005.0,
        "value": 1625.0
      },
      {
        "year": 2006.0,
        "value": 7424.0
      },
      {
        "year": 2007.0,
        "value": 7769.0
      },
      {
        "year": 2008.0,
        "value": 5432.0
      },
      {
        "year": 2009.0,
        "value": 2805.0
      },
      {
        "year": 2010.0,
        "value": 2492.0
      },
      {
        "year": 2011.0,
        "value": -1957.0
      },
      {
        "year": 2012.0,
        "value": 3207.0
      },
      {
        "year": 2013.0,
        "value": 3598.0
      },
      {
        "year": 2014.0,
        "value": 2828.0
      },
      {
        "year": 2015.0,
        "value": 2391.0
      },
      {
        "year": 2016.0,
        "value": 9692.0
      },
      {
        "year": 2017.0,
        "value": 3401.0
      },
      {
        "year": 2018.0,
        "value": 7114.0
      },
      {
        "year": 2019.0,
        "value": 8240.0
      },
      {
        "year": 2020.0,
        "value": 8802.0
      }
    ],
    "targets": null
  },
  {
    "Type of speed": "ANYS",
    "Reporting Type": "G",
    "series": "IT_NET_BBNDN",
    "goal": "17",
    "target": "17.6",
    "indicator": "17.6.1",
    "seriesDescription": "Number of fixed Internet broadband subscriptions, by speed (number)",
    "values": [
      {
        "year": 2000.0,
        "value": 229000.0
      },
      {
        "year": 2001.0,
        "value": 1133000.0
      },
      {
        "year": 2002.0,
        "value": 2100000.0
      },
      {
        "year": 2003.0,
        "value": 3043273.0
      },
      {
        "year": 2004.0,
        "value": 3751214.0
      },
      {
        "year": 2005.0,
        "value": 4340889.0
      },
      {
        "year": 2006.0,
        "value": 4505800.0
      },
      {
        "year": 2007.0,
        "value": 4790191.0
      },
      {
        "year": 2008.0,
        "value": 5024378.0
      },
      {
        "year": 2009.0,
        "value": 4997719.0
      },
      {
        "year": 2010.0,
        "value": 5311603.0
      },
      {
        "year": 2011.0,
        "value": 5515932.0
      },
      {
        "year": 2012.0,
        "value": 6448823.0
      },
      {
        "year": 2013.0,
        "value": 7011934.0
      },
      {
        "year": 2014.0,
        "value": 7436620.0
      },
      {
        "year": 2015.0,
        "value": 5656330.0
      },
      {
        "year": 2016.0,
        "value": 5686003.0
      },
      {
        "year": 2017.0,
        "value": 5713568.0
      },
      {
        "year": 2018.0,
        "value": 5725022.0
      },
      {
        "year": 2019.0,
        "value": 5831467.0
      }
    ],
    "targets": null
  },
  {
    "Type of speed": "2MT10MBPS",
    "Reporting Type": "G",
    "series": "IT_NET_BBNDN",
    "goal": "17",
    "target": "17.6",
    "indicator": "17.6.1",
    "seriesDescription": "Number of fixed Internet broadband subscriptions, by speed (number)",
    "values": [
      {
        "year": 2009.0,
        "value": 2156367.0
      },
      {
        "year": 2010.0,
        "value": 2159739.0
      },
      {
        "year": 2011.0,
        "value": 2099183.0
      },
      {
        "year": 2012.0,
        "value": 1981845.0
      },
      {
        "year": 2013.0,
        "value": 2004886.0
      },
      {
        "year": 2014.0,
        "value": 3664647.0
      },
      {
        "year": 2015.0,
        "value": 1662106.0
      },
      {
        "year": 2016.0,
        "value": 1363908.0
      },
      {
        "year": 2017.0,
        "value": 1027478.0
      },
      {
        "year": 2018.0,
        "value": 873425.0
      },
      {
        "year": 2019.0,
        "value": 556737.0
      }
    ],
    "targets": null
  },
  {
    "Type of speed": "256KT2MBPS",
    "Reporting Type": "G",
    "series": "IT_NET_BBNDN",
    "goal": "17",
    "target": "17.6",
    "indicator": "17.6.1",
    "seriesDescription": "Number of fixed Internet broadband subscriptions, by speed (number)",
    "values": [
      {
        "year": 2009.0,
        "value": 1185344.0
      },
      {
        "year": 2010.0,
        "value": 858621.0
      },
      {
        "year": 2011.0,
        "value": 819761.0
      },
      {
        "year": 2012.0,
        "value": 717045.0
      },
      {
        "year": 2013.0,
        "value": 446253.0
      },
      {
        "year": 2014.0,
        "value": 403284.0
      },
      {
        "year": 2015.0,
        "value": 315658.0
      },
      {
        "year": 2016.0,
        "value": 256675.0
      },
      {
        "year": 2017.0,
        "value": 219925.0
      },
      {
        "year": 2018.0,
        "value": 171804.0
      },
      {
        "year": 2019.0,
        "value": 140296.0
      }
    ],
    "targets": null
  },
  {
    "Type of speed": "10MBPS",
    "Reporting Type": "G",
    "series": "IT_NET_BBNDN",
    "goal": "17",
    "target": "17.6",
    "indicator": "17.6.1",
    "seriesDescription": "Number of fixed Internet broadband subscriptions, by speed (number)",
    "values": [
      {
        "year": 2009.0,
        "value": 1656004.0
      },
      {
        "year": 2010.0,
        "value": 2246666.0
      },
      {
        "year": 2011.0,
        "value": 2545138.0
      },
      {
        "year": 2012.0,
        "value": 2862821.0
      },
      {
        "year": 2013.0,
        "value": 3182861.0
      },
      {
        "year": 2014.0,
        "value": 3368689.0
      },
      {
        "year": 2015.0,
        "value": 3678566.0
      },
      {
        "year": 2016.0,
        "value": 4065420.0
      },
      {
        "year": 2017.0,
        "value": 4466165.0
      },
      {
        "year": 2018.0,
        "value": 4679793.0
      },
      {
        "year": 2019.0,
        "value": 5134434.0
      }
    ],
    "targets": null
  },
  {
    "Type of speed": "ANYS",
    "Reporting Type": "G",
    "series": "IT_NET_BBND",
    "goal": "17",
    "target": "17.6",
    "indicator": "17.6.1",
    "seriesDescription": "Fixed Internet broadband subscriptions per 100\u00a0inhabitants, by speed (per 100 inhabitants)",
    "values": [
      {
        "year": 2000.0,
        "value": 1.0425
      },
      {
        "year": 2001.0,
        "value": 5.12468
      },
      {
        "year": 2002.0,
        "value": 9.43299
      },
      {
        "year": 2003.0,
        "value": 13.57405
      },
      {
        "year": 2004.0,
        "value": 16.62019
      },
      {
        "year": 2005.0,
        "value": 19.11805
      },
      {
        "year": 2006.0,
        "value": 19.74163
      },
      {
        "year": 2007.0,
        "value": 20.89303
      },
      {
        "year": 2008.0,
        "value": 21.82705
      },
      {
        "year": 2009.0,
        "value": 21.63089
      },
      {
        "year": 2010.0,
        "value": 22.90713
      },
      {
        "year": 2011.0,
        "value": 23.70531
      },
      {
        "year": 2012.0,
        "value": 27.62176
      },
      {
        "year": 2013.0,
        "value": 29.93792
      },
      {
        "year": 2014.0,
        "value": 24.13426
      },
      {
        "year": 2015.0,
        "value": 24.01076
      },
      {
        "year": 2016.0,
        "value": 24.07467
      },
      {
        "year": 2017.0,
        "value": 24.1338
      },
      {
        "year": 2018.0,
        "value": 24.12927
      },
      {
        "year": 2019.0,
        "value": 24.52889
      },
      {
        "year": 2020.0,
        "value": 25.40188
      }
    ],
    "targets": null
  },
  {
    "Type of speed": "256KT2MBPS",
    "Reporting Type": "G",
    "series": "IT_NET_BBND",
    "goal": "17",
    "target": "17.6",
    "indicator": "17.6.1",
    "seriesDescription": "Fixed Internet broadband subscriptions per 100\u00a0inhabitants, by speed (per 100 inhabitants)",
    "values": [
      {
        "year": 2009.0,
        "value": 5.13035
      },
      {
        "year": 2010.0,
        "value": 3.70294
      },
      {
        "year": 2011.0,
        "value": 3.52301
      },
      {
        "year": 2012.0,
        "value": 3.07126
      },
      {
        "year": 2013.0,
        "value": 1.90531
      },
      {
        "year": 2014.0,
        "value": 1.71669
      },
      {
        "year": 2015.0,
        "value": 1.33995
      },
      {
        "year": 2016.0,
        "value": 1.08677
      },
      {
        "year": 2017.0,
        "value": 0.92895
      },
      {
        "year": 2018.0,
        "value": 0.7241
      },
      {
        "year": 2019.0,
        "value": 0.59013
      },
      {
        "year": 2020.0,
        "value": 0.12828
      }
    ],
    "targets": null
  },
  {
    "Type of speed": "10MBPS",
    "Reporting Type": "G",
    "series": "IT_NET_BBND",
    "goal": "17",
    "target": "17.6",
    "indicator": "17.6.1",
    "seriesDescription": "Fixed Internet broadband subscriptions per 100\u00a0inhabitants, by speed (per 100 inhabitants)",
    "values": [
      {
        "year": 2009.0,
        "value": 7.16744
      },
      {
        "year": 2010.0,
        "value": 9.6891
      },
      {
        "year": 2011.0,
        "value": 10.938
      },
      {
        "year": 2012.0,
        "value": 12.26211
      },
      {
        "year": 2013.0,
        "value": 13.58944
      },
      {
        "year": 2014.0,
        "value": 14.33974
      },
      {
        "year": 2015.0,
        "value": 15.61528
      },
      {
        "year": 2016.0,
        "value": 17.21308
      },
      {
        "year": 2017.0,
        "value": 18.86484
      },
      {
        "year": 2018.0,
        "value": 19.72394
      },
      {
        "year": 2019.0,
        "value": 21.59696
      },
      {
        "year": 2020.0,
        "value": 23.04698
      }
    ],
    "targets": null
  },
  {
    "Type of speed": "2MT10MBPS",
    "Reporting Type": "G",
    "series": "IT_NET_BBND",
    "goal": "17",
    "target": "17.6",
    "indicator": "17.6.1",
    "seriesDescription": "Fixed Internet broadband subscriptions per 100\u00a0inhabitants, by speed (per 100 inhabitants)",
    "values": [
      {
        "year": 2009.0,
        "value": 9.33309
      },
      {
        "year": 2010.0,
        "value": 9.31422
      },
      {
        "year": 2011.0,
        "value": 9.02146
      },
      {
        "year": 2012.0,
        "value": 8.48869
      },
      {
        "year": 2013.0,
        "value": 8.55999
      },
      {
        "year": 2014.0,
        "value": 8.07783
      },
      {
        "year": 2015.0,
        "value": 7.05553
      },
      {
        "year": 2016.0,
        "value": 5.77482
      },
      {
        "year": 2017.0,
        "value": 4.34001
      },
      {
        "year": 2018.0,
        "value": 3.68123
      },
      {
        "year": 2019.0,
        "value": 2.3418
      },
      {
        "year": 2020.0,
        "value": 2.22662
      }
    ],
    "targets": null
  },
  {
    "Reporting Type": "G",
    "series": "IT_USE_ii99",
    "goal": "17",
    "target": "17.8",
    "indicator": "17.8.1",
    "seriesDescription": "Internet users per 100 inhabitants",
    "values": [
      {
        "year": 2000.0,
        "value": 28.10115
      },
      {
        "year": 2001.0,
        "value": 34.90204
      },
      {
        "year": 2002.0,
        "value": 47.60049
      },
      {
        "year": 2003.0,
        "value": 51.93645
      },
      {
        "year": 2004.0,
        "value": 53.81433
      },
      {
        "year": 2005.0,
        "value": 58.01493
      },
      {
        "year": 2006.0,
        "value": 63.68421
      },
      {
        "year": 2007.0,
        "value": 64.45
      },
      {
        "year": 2008.0,
        "value": 65.84
      },
      {
        "year": 2009.0,
        "value": 69.9
      },
      {
        "year": 2010.0,
        "value": 71.5
      },
      {
        "year": 2011.0,
        "value": 72.0
      },
      {
        "year": 2012.0,
        "value": 75.9908
      },
      {
        "year": 2013.0,
        "value": 76.28917
      },
      {
        "year": 2014.0,
        "value": 78.03762
      },
      {
        "year": 2015.0,
        "value": 78.03687
      },
      {
        "year": 2016.0,
        "value": 79.74519
      },
      {
        "year": 2017.0,
        "value": 82.9
      },
      {
        "year": 2018.0,
        "value": 86.20581
      },
      {
        "year": 2019.0,
        "value": 88.82246
      },
      {
        "year": 2020.0,
        "value": 89.0
      }
    ],
    "targets": {
      "targetValue": 90,
      "type": "max"
    }
  },
  {
    "Age": "10-14",
    "Sex": "FEMALE",
    "Reporting Type": "G",
    "series": "SP_DYN_ADKL",
    "goal": "3",
    "target": "3.7",
    "indicator": "3.7.2",
    "seriesDescription": "Adolescent birth rate (per 1,000 women aged 15-19 and 10-14 years)",
    "values": [
      {
        "year": 2000.0,
        "value": 0.4
      },
      {
        "year": 2001.0,
        "value": 0.4
      },
      {
        "year": 2002.0,
        "value": 0.3
      },
      {
        "year": 2003.0,
        "value": 0.2
      },
      {
        "year": 2004.0,
        "value": 0.2
      },
      {
        "year": 2005.0,
        "value": 0.2
      },
      {
        "year": 2006.0,
        "value": 0.2
      },
      {
        "year": 2007.0,
        "value": 0.1
      },
      {
        "year": 2008.0,
        "value": 0.1
      },
      {
        "year": 2009.0,
        "value": 0.1
      },
      {
        "year": 2010.0,
        "value": 0.1
      },
      {
        "year": 2011.0,
        "value": 0.1
      },
      {
        "year": 2012.0,
        "value": 0.1
      },
      {
        "year": 2013.0,
        "value": 0.1
      },
      {
        "year": 2014.0,
        "value": 0.1
      },
      {
        "year": 2015.0,
        "value": 0.1
      },
      {
        "year": 2016.0,
        "value": 0.1
      },
      {
        "year": 2017.0,
        "value": 0.1
      },
      {
        "year": 2018.0,
        "value": 0.1
      },
      {
        "year": 2019.0,
        "value": 0.1
      }
    ],
    "targets": null
  },
  {
    "Age": "15-19",
    "Sex": "FEMALE",
    "Reporting Type": "G",
    "series": "SP_DYN_ADKL",
    "goal": "3",
    "target": "3.7",
    "indicator": "3.7.2",
    "seriesDescription": "Adolescent birth rate (per 1,000 women aged 15-19 and 10-14 years)",
    "values": [
      {
        "year": 2001.0,
        "value": 12.6
      },
      {
        "year": 2002.0,
        "value": 11.7
      },
      {
        "year": 2003.0,
        "value": 11.0
      },
      {
        "year": 2004.0,
        "value": 10.0
      },
      {
        "year": 2005.0,
        "value": 8.4
      },
      {
        "year": 2006.0,
        "value": 7.0
      },
      {
        "year": 2007.0,
        "value": 6.0
      },
      {
        "year": 2008.0,
        "value": 5.0
      },
      {
        "year": 2009.0,
        "value": 4.0
      },
      {
        "year": 2010.0,
        "value": 4.0
      },
      {
        "year": 2011.0,
        "value": 4.0
      },
      {
        "year": 2012.0,
        "value": 4.0
      },
      {
        "year": 2013.0,
        "value": 4.0
      },
      {
        "year": 2014.0,
        "value": 4.0
      },
      {
        "year": 2015.0,
        "value": 4.0
      },
      {
        "year": 2016.0,
        "value": 4.0
      },
      {
        "year": 2017.0,
        "value": 4.0
      },
      {
        "year": 2018.0,
        "value": 3.8
      },
      {
        "year": 2019.0,
        "value": 3.8
      }
    ],
    "targets": null
  },
  {
    "Sex": "MALE",
    "Reporting Type": "G",
    "series": "IT_MOB_OWN",
    "goal": "5",
    "target": "5.b",
    "indicator": "5.b.1",
    "seriesDescription": "Proportion of individuals who own a mobile telephone, by sex (%)",
    "values": [
      {
        "year": 2017.0,
        "value": 97.6
      },
      {
        "year": 2018.0,
        "value": 95.26
      },
      {
        "year": 2019.0,
        "value": 97.44991
      }
    ],
    "targets": null
  },
  {
    "Sex": "BOTHSEX",
    "Reporting Type": "G",
    "series": "IT_MOB_OWN",
    "goal": "5",
    "target": "5.b",
    "indicator": "5.b.1",
    "seriesDescription": "Proportion of individuals who own a mobile telephone, by sex (%)",
    "values": [
      {
        "year": 2017.0,
        "value": 97.54936
      },
      {
        "year": 2018.0,
        "value": 95.59987
      },
      {
        "year": 2019.0,
        "value": 96.14286
      },
      {
        "year": 2020.0,
        "value": 95.37643
      }
    ],
    "targets": null
  },
  {
    "Sex": "FEMALE",
    "Reporting Type": "G",
    "series": "IT_MOB_OWN",
    "goal": "5",
    "target": "5.b",
    "indicator": "5.b.1",
    "seriesDescription": "Proportion of individuals who own a mobile telephone, by sex (%)",
    "values": [
      {
        "year": 2017.0,
        "value": 97.5
      },
      {
        "year": 2018.0,
        "value": 95.93
      },
      {
        "year": 2019.0,
        "value": 94.87633
      }
    ],
    "targets": null
  },
  {
    "Mode of transportation": "AIR",
    "Reporting Type": "G",
    "series": "IS_RDP_FRGVOL",
    "goal": "9",
    "target": "9.1",
    "indicator": "9.1.2",
    "seriesDescription": "Freight volume, by mode of transport (tonne kilometres)",
    "values": [
      {
        "year": 2017.0,
        "value": 9366859882.0
      }
    ],
    "targets": null
  },
  {
    "Mode of transportation": "AIR",
    "Reporting Type": "G",
    "series": "IS_RDP_PFVOL",
    "goal": "9",
    "target": "9.1",
    "indicator": "9.1.2",
    "seriesDescription": "Passenger volume (passenger kilometres), by mode of transport",
    "values": [
      {
        "year": 2017.0,
        "value": 92234268647.0
      }
    ],
    "targets": null
  },
  {
    "Reporting Type": "G",
    "Mode of transportation": "SEA",
    "series": "IS_RDP_PORFVOL",
    "goal": "9",
    "target": "9.1",
    "indicator": "9.1.2",
    "seriesDescription": "Container port traffic, maritime transport (twenty-foot equivalent units - TEUs)",
    "values": [
      {
        "year": 2010.0,
        "value": 12497000.0
      },
      {
        "year": 2011.0,
        "value": 13423000.0
      },
      {
        "year": 2012.0,
        "value": 13878000.0
      },
      {
        "year": 2013.0,
        "value": 14046700.0
      },
      {
        "year": 2014.0,
        "value": 15050100.0
      },
      {
        "year": 2015.0,
        "value": 14491800.0
      },
      {
        "year": 2016.0,
        "value": 14865000.0
      },
      {
        "year": 2017.0,
        "value": 14911000.0
      },
      {
        "year": 2018.0,
        "value": 15321600.0
      },
      {
        "year": 2019.0,
        "value": 15298300.0
      },
      {
        "year": 2020.0,
        "value": 14593600.0
      }
    ],
    "targets": null
  },
  {
    "Reporting Type": "G",
    "Activity": "ISIC4_C",
    "series": "NV_IND_MANFPC",
    "goal": "9",
    "target": "9.2",
    "indicator": "9.2.1",
    "seriesDescription": "Manufacturing value added per capita (constant 2015 United States dollars)",
    "values": [
      {
        "year": 2000.0,
        "value": 2741.54
      },
      {
        "year": 2001.0,
        "value": 2536.92
      },
      {
        "year": 2002.0,
        "value": 2820.89
      },
      {
        "year": 2003.0,
        "value": 3122.6
      },
      {
        "year": 2004.0,
        "value": 3462.7
      },
      {
        "year": 2005.0,
        "value": 3745.2
      },
      {
        "year": 2006.0,
        "value": 4022.78
      },
      {
        "year": 2007.0,
        "value": 4594.01
      },
      {
        "year": 2008.0,
        "value": 4632.65
      },
      {
        "year": 2009.0,
        "value": 4522.94
      },
      {
        "year": 2010.0,
        "value": 5557.82
      },
      {
        "year": 2011.0,
        "value": 5905.22
      },
      {
        "year": 2012.0,
        "value": 6200.84
      },
      {
        "year": 2013.0,
        "value": 6390.13
      },
      {
        "year": 2014.0,
        "value": 7041.58
      },
      {
        "year": 2015.0,
        "value": 7116.14
      },
      {
        "year": 2016.0,
        "value": 7384.84
      },
      {
        "year": 2017.0,
        "value": 7767.89
      },
      {
        "year": 2018.0,
        "value": 7950.18
      },
      {
        "year": 2019.0,
        "value": 8021.02
      },
      {
        "year": 2020.0,
        "value": 8596.21
      },
      {
        "year": 2021.0,
        "value": 9773.61
      }
    ],
    "targets": {
      "targetValue": 20,
      "type": "max"
    }
  },
  {
    "Reporting Type": "G",
    "Activity": "ISIC4_C",
    "series": "NV_IND_MANF",
    "goal": "9",
    "target": "9.2",
    "indicator": "9.2.1",
    "seriesDescription": "Manufacturing value added (constant 2015 United States dollars) as a proportion of GDP (%)",
    "values": [
      {
        "year": 2000.0,
        "value": 19.63
      },
      {
        "year": 2001.0,
        "value": 18.54
      },
      {
        "year": 2002.0,
        "value": 19.68
      },
      {
        "year": 2003.0,
        "value": 21.05
      },
      {
        "year": 2004.0,
        "value": 21.97
      },
      {
        "year": 2005.0,
        "value": 22.69
      },
      {
        "year": 2006.0,
        "value": 23.16
      },
      {
        "year": 2007.0,
        "value": 24.86
      },
      {
        "year": 2008.0,
        "value": 24.97
      },
      {
        "year": 2009.0,
        "value": 24.88
      },
      {
        "year": 2010.0,
        "value": 27.83
      },
      {
        "year": 2011.0,
        "value": 28.62
      },
      {
        "year": 2012.0,
        "value": 29.5
      },
      {
        "year": 2013.0,
        "value": 29.75
      },
      {
        "year": 2014.0,
        "value": 31.4
      },
      {
        "year": 2015.0,
        "value": 31.36
      },
      {
        "year": 2016.0,
        "value": 31.94
      },
      {
        "year": 2017.0,
        "value": 32.6
      },
      {
        "year": 2018.0,
        "value": 32.53
      },
      {
        "year": 2019.0,
        "value": 31.91
      },
      {
        "year": 2020.0,
        "value": 33.14
      },
      {
        "year": 2021.0,
        "value": 35.46
      }
    ],
    "targets": {
      "targetValue": 20,
      "type": "max"
    }
  },
  {
    "Reporting Type": "G",
    "Activity": "ISIC4_C",
    "series": "NV_IND_MANF_CD",
    "goal": "9",
    "target": "9.2",
    "indicator": "9.2.1",
    "seriesDescription": "Manufacturing value added (current United States dollars) as a proportion of GDP (%)",
    "values": [
      {
        "year": 2000.0,
        "value": 25.27
      },
      {
        "year": 2001.0,
        "value": 23.59
      },
      {
        "year": 2002.0,
        "value": 25.45
      },
      {
        "year": 2003.0,
        "value": 26.86
      },
      {
        "year": 2004.0,
        "value": 27.63
      },
      {
        "year": 2005.0,
        "value": 27.31
      },
      {
        "year": 2006.0,
        "value": 27.15
      },
      {
        "year": 2007.0,
        "value": 27.63
      },
      {
        "year": 2008.0,
        "value": 26.65
      },
      {
        "year": 2009.0,
        "value": 25.96
      },
      {
        "year": 2010.0,
        "value": 28.6
      },
      {
        "year": 2011.0,
        "value": 28.27
      },
      {
        "year": 2012.0,
        "value": 28.07
      },
      {
        "year": 2013.0,
        "value": 29.11
      },
      {
        "year": 2014.0,
        "value": 31.1
      },
      {
        "year": 2015.0,
        "value": 31.36
      },
      {
        "year": 2016.0,
        "value": 32.22
      },
      {
        "year": 2017.0,
        "value": 32.66
      },
      {
        "year": 2018.0,
        "value": 32.27
      },
      {
        "year": 2019.0,
        "value": 30.92
      },
      {
        "year": 2020.0,
        "value": 31.93
      },
      {
        "year": 2021.0,
        "value": 32.79
      }
    ],
    "targets": {
      "targetValue": 20,
      "type": "max"
    }
  },
  {
    "Reporting Type": "G",
    "Activity": "ISIC4_C",
    "series": "EN_ATM_CO2MVA",
    "goal": "9",
    "target": "9.4",
    "indicator": "9.4.1",
    "seriesDescription": "Carbon dioxide emissions per unit of manufacturing value added (kilogrammes of CO2 per constant 2015 United States dollars)",
    "values": [
      {
        "year": 2000.0,
        "value": 0.71
      },
      {
        "year": 2001.0,
        "value": 0.73
      },
      {
        "year": 2002.0,
        "value": 0.69
      },
      {
        "year": 2003.0,
        "value": 0.592
      },
      {
        "year": 2004.0,
        "value": 0.538
      },
      {
        "year": 2005.0,
        "value": 0.487
      },
      {
        "year": 2006.0,
        "value": 0.466
      },
      {
        "year": 2007.0,
        "value": 0.398
      },
      {
        "year": 2008.0,
        "value": 0.355
      },
      {
        "year": 2009.0,
        "value": 0.338
      },
      {
        "year": 2010.0,
        "value": 0.31
      },
      {
        "year": 2011.0,
        "value": 0.297
      },
      {
        "year": 2012.0,
        "value": 0.273
      },
      {
        "year": 2013.0,
        "value": 0.272
      },
      {
        "year": 2014.0,
        "value": 0.227
      },
      {
        "year": 2015.0,
        "value": 0.219
      },
      {
        "year": 2016.0,
        "value": 0.213
      },
      {
        "year": 2017.0,
        "value": 0.193
      },
      {
        "year": 2018.0,
        "value": 0.171
      },
      {
        "year": 2019.0,
        "value": 0.166
      }
    ],
    "targets": null
  },
  {
    "Reporting Type": "G",
    "Activity": "ISIC4_C",
    "series": "NV_IND_TECH",
    "goal": "9",
    "target": "9.b",
    "indicator": "9.b.1",
    "seriesDescription": "Proportion of medium and high-tech manufacturing value added in total value added (%)",
    "values": [
      {
        "year": 2000.0,
        "value": 56.21
      },
      {
        "year": 2001.0,
        "value": 55.32
      },
      {
        "year": 2002.0,
        "value": 58.58
      },
      {
        "year": 2003.0,
        "value": 61.5
      },
      {
        "year": 2004.0,
        "value": 62.58
      },
      {
        "year": 2005.0,
        "value": 63.63
      },
      {
        "year": 2006.0,
        "value": 65.46
      },
      {
        "year": 2007.0,
        "value": 65.93
      },
      {
        "year": 2008.0,
        "value": 67.25
      },
      {
        "year": 2009.0,
        "value": 66.89
      },
      {
        "year": 2010.0,
        "value": 67.91
      },
      {
        "year": 2011.0,
        "value": 67.69
      },
      {
        "year": 2012.0,
        "value": 68.49
      },
      {
        "year": 2013.0,
        "value": 68.77
      },
      {
        "year": 2014.0,
        "value": 70.81
      },
      {
        "year": 2015.0,
        "value": 69.46
      },
      {
        "year": 2016.0,
        "value": 68.66
      },
      {
        "year": 2017.0,
        "value": 69.09
      },
      {
        "year": 2018.0,
        "value": 68.66
      },
      {
        "year": 2019.0,
        "value": 68.43
      }
    ],
    "targets": null
  },
  {
    "Reporting Type": "G",
    "series": "IT_MOB_2GNTWK",
    "goal": "9",
    "target": "9.c",
    "indicator": "9.c.1",
    "seriesDescription": "Proportion of population covered by at least a 2G mobile network (%)",
    "values": [
      {
        "year": 2000.0,
        "value": 100.0
      },
      {
        "year": 2001.0,
        "value": 100.0
      },
      {
        "year": 2002.0,
        "value": 100.0
      },
      {
        "year": 2003.0,
        "value": 100.0
      },
      {
        "year": 2004.0,
        "value": 100.0
      },
      {
        "year": 2005.0,
        "value": 100.0
      },
      {
        "year": 2006.0,
        "value": 100.0
      },
      {
        "year": 2007.0,
        "value": 100.0
      },
      {
        "year": 2008.0,
        "value": 100.0
      },
      {
        "year": 2009.0,
        "value": 100.0
      },
      {
        "year": 2010.0,
        "value": 100.0
      },
      {
        "year": 2011.0,
        "value": 100.0
      },
      {
        "year": 2012.0,
        "value": 100.0
      },
      {
        "year": 2013.0,
        "value": 100.0
      },
      {
        "year": 2014.0,
        "value": 100.0
      },
      {
        "year": 2015.0,
        "value": 100.0
      },
      {
        "year": 2016.0,
        "value": 100.0
      },
      {
        "year": 2017.0,
        "value": 100.0
      },
      {
        "year": 2018.0,
        "value": 100.0
      },
      {
        "year": 2019.0,
        "value": 100.0
      },
      {
        "year": 2020.0,
        "value": 100.0
      }
    ],
    "targets": {
      "targetValue": 99.9,
      "type": "max"
    }
  },
  {
    "Reporting Type": "G",
    "series": "IT_MOB_3GNTWK",
    "goal": "9",
    "target": "9.c",
    "indicator": "9.c.1",
    "seriesDescription": "Proportion of population covered by at least a 3G mobile network (%)",
    "values": [
      {
        "year": 2007.0,
        "value": 76.0
      },
      {
        "year": 2008.0,
        "value": 85.0
      },
      {
        "year": 2009.0,
        "value": 90.0
      },
      {
        "year": 2010.0,
        "value": 93.0
      },
      {
        "year": 2011.0,
        "value": 96.0
      },
      {
        "year": 2012.0,
        "value": 98.0
      },
      {
        "year": 2013.0,
        "value": 99.0
      },
      {
        "year": 2014.0,
        "value": 100.0
      },
      {
        "year": 2015.0,
        "value": 100.0
      },
      {
        "year": 2016.0,
        "value": 100.0
      },
      {
        "year": 2017.0,
        "value": 100.0
      },
      {
        "year": 2018.0,
        "value": 100.0
      },
      {
        "year": 2019.0,
        "value": 100.0
      },
      {
        "year": 2020.0,
        "value": 100.0
      }
    ],
    "targets": {
      "targetValue": 99.9,
      "type": "max"
    }
  },
  {
    "Reporting Type": "G",
    "series": "IT_MOB_4GNTWK",
    "goal": "9",
    "target": "9.c",
    "indicator": "9.c.1",
    "seriesDescription": "Proportion of population covered by at least a 4G mobile network (%)",
    "values": [
      {
        "year": 2014.0,
        "value": 99.3
      },
      {
        "year": 2015.0,
        "value": 99.45
      },
      {
        "year": 2016.0,
        "value": 99.5
      },
      {
        "year": 2017.0,
        "value": 99.6
      },
      {
        "year": 2018.0,
        "value": 99.9
      },
      {
        "year": 2019.0,
        "value": 99.9
      },
      {
        "year": 2020.0,
        "value": 99.8
      }
    ],
    "targets": {
      "targetValue": 99.9,
      "type": "max"
    }
  }
]